sortingalgos/Bubble_sort.py
sortingalgos/Insertion_sort.py
sortingalgos/Quick_sort.py
sortingalgos/Selection_sort.py
sortingalgos/__init__.py
sortingalgos/print.py
sortingalgos-0.1.dist-info/METADATA
sortingalgos-0.1.dist-info/WHEEL
sortingalgos-0.1.dist-info/top_level.txt
sortingalgos-0.1.dist-info/RECORD
